{
  "session_id": "20251014_131928",
  "session_start": "2025-10-14T13:19:28.649070",
  "file_format": "csv",
  "compression": false,
  "buffer_size": 1000,
  "max_file_size_mb": 100.0,
  "output_directory": "data/raw",
  "stats": {
    "total_entries": 2081,
    "entries_since_last_export": 2081,
    "total_exports": 0,
    "files_created": 1,
    "bytes_written": 166480,
    "session_start": "2025-10-14T13:19:28.649070",
    "last_entry_time": "2025-10-14T13:20:50.847330",
    "last_export_time": null
  }
}